COPYING.gplv3
README.rst
setup.cfg
setup.py
kdbx_1pif_importer/__init__.py
kdbx_1pif_importer.egg-info/PKG-INFO
kdbx_1pif_importer.egg-info/SOURCES.txt
kdbx_1pif_importer.egg-info/dependency_links.txt
kdbx_1pif_importer.egg-info/entry_points.txt
kdbx_1pif_importer.egg-info/requires.txt
kdbx_1pif_importer.egg-info/top_level.txt
kdbx_1pif_importer.egg-info/zip-safe