Metadata-Version: 2.1
Name: kdbx-1pif-importer
Version: 0.0.5
Summary: Import 1Password exported .1pif into KeePass.
Home-page: UNKNOWN
Author: Bheesham Persaud
Author-email: me@bheesham.com
License: UNKNOWN
Keywords: 1password keepass pykeepass
Platform: UNKNOWN
Classifier: License :: OSI Approved :: GNU General Public License v3 or later (GPLv3+)
Classifier: Programming Language :: Python :: 3.9
Classifier: Topic :: Utilities
Requires-Python: >=3.6
